randomframe/__init__.py
randomframe-0.3.dist-info/LICENSE
randomframe-0.3.dist-info/METADATA
randomframe-0.3.dist-info/WHEEL
randomframe-0.3.dist-info/top_level.txt
randomframe-0.3.dist-info/RECORD
