Metadata-Version: 2.1
Name: randomframe
Version: 0.3
Summary: Random Frame backend
Home-page: https://git.automatia.nl/ShadowJonathan/randomframe
Author: Jonathan de Jong
Author-email: jonathan@automatia.nl
License: UNKNOWN
Platform: UNKNOWN
Classifier: Programming Language :: Python :: 3
Classifier: License :: OSI Approved :: MIT License
Classifier: Operating System :: OS Independent
Requires-Dist: requests
Requires-Dist: flask
Requires-Dist: base58
Provides-Extra: dev
Requires-Dist: ipython ; extra == 'dev'
Requires-Dist: twine ; extra == 'dev'
Requires-Dist: bump2version ; extra == 'dev'
Requires-Dist: black ; extra == 'dev'
